Full Adder/FA.v
`timescale 1ns/1ps

module full_adder (
    input a, b, c_in,
    output sum, c_out
);
    assign sum = a ^ b ^ c_in;
    assign c_out = (a & b) | (a & c_in) | (b & c_in);
endmodule

Full Adder/FA_tb.v
`timescale 1ns/1ps

module full_adder_tb;
    reg a, b, c_in;
    wire sum, c_out;

    // Instantiate the design under test (DUT)
    full_adder dut (
        .a(a),
        .b(b),
        .c_in(c_in),
        .sum(sum),
        .c_out(c_out)
    );

    initial begin

	$dumpfile("FA_tb.vcd");
	$dumpvars(0, full_adder_tb);

        $display("Testing Full Adder");
        $monitor("a=%b b=%b c_in=%b => sum=%b c_out=%b", a, b, c_in, sum, c_out);

        a = 0; b = 0; c_in = 0; #10;
        a = 0; b = 0; c_in = 1; #10;
        a = 0; b = 1; c_in = 0; #10;
        a = 0; b = 1; c_in = 1; #10;
        a = 1; b = 0; c_in = 0; #10;
        a = 1; b = 0; c_in = 1; #10;
        a = 1; b = 1; c_in = 0; #10;
        a = 1; b = 1; c_in = 1; #10;

        $finish;
    end
endmodule

Full Adder/FA_tb.vcd
$date
	Sun May 04 20:59:38 2025
$end
$version
	Icarus Verilog
$end
$timescale
	1ps
$end
$scope module full_adder_tb $end
$var wire 1 ! sum $end
$var wire 1 " c_out $end
$var reg 1 # a $end
$var reg 1 $ b $end
$var reg 1 % c_in $end
$scope module dut $end
$var wire 1 # a $end
$var wire 1 $ b $end
$var wire 1 % c_in $end
$var wire 1 " c_out $end
$var wire 1 ! sum $end
$upscope $end
$upscope $end
$enddefinitions $end
$comment Show the parameter values. $end
$dumpall
$end
#0
$dumpvars
0%
0$
0#
0"
0!
$end
#10000
1!
1%
#20000
0%
1$
#30000
1"
0!
1%
#40000
0"
1!
0%
0$
1#
#50000
1"
0!
1%
#60000
0%
1$
#70000
1!
1%
