3-to-8_Decoder/3-8Decoder.v
//3-to-8 Decoder (Structural)
module decoder3to8_struct(
    input [2:0] in,
    output [7:0] out
);
    assign out[0] = ~in[2] & ~in[1] & ~in[0];
    assign out[1] = ~in[2] & ~in[1] &  in[0];
    assign out[2] = ~in[2] &  in[1] & ~in[0];
    assign out[3] = ~in[2] &  in[1] &  in[0];
    assign out[4] =  in[2] & ~in[1] & ~in[0];
    assign out[5] =  in[2] & ~in[1] &  in[0];
    assign out[6] =  in[2] &  in[1] & ~in[0];
    assign out[7] =  in[2] &  in[1] &  in[0];
endmodule

//3-to-8 Decoder (Behavioral)
module decoder3to8_beh(
    input [2:0] in,
    output reg [7:0] out
);
    always @(*) begin
        out = 8'b00000000;
        out[in] = 1'b1;
    end
endmodule

3-to-8_Decoder/3-8Decoder_tb.v
module tb_decoder3to8;
    reg [2:0] in;
    wire [7:0] out_struct, out_beh;

    decoder3to8_struct ds (.in(in), .out(out_struct));
    decoder3to8_beh db (.in(in), .out(out_beh));

    initial begin
        $dumpfile("3-8Decoder_tb.vcd");
        $dumpvars(0, tb_decoder3to8);
        $display("In  | Out_Struct  |  Out_Beh");
        $monitor("%b | %b    |  %b", in, out_struct, out_beh);
        in = 3'b000; #10;
        in = 3'b001; #10;
        in = 3'b010; #10;
        in = 3'b011; #10;
        in = 3'b100; #10;
        in = 3'b101; #10;
        in = 3'b110; #10;
        in = 3'b111; #10;
        $finish;
    end
endmodule

3-to-8_Decoder/3-8Decoder_tb.vcd
$date
	Thu May 15 00:15:58 2025
$end
$version
	Icarus Verilog
$end
$timescale
	1s
$end
$scope module tb_decoder3to8 $end
$var wire 8 ! out_struct [7:0] $end
$var wire 8 " out_beh [7:0] $end
$var reg 3 # in [2:0] $end
$scope module db $end
$var wire 3 $ in [2:0] $end
$var reg 8 % out [7:0] $end
$upscope $end
$scope module ds $end
$var wire 3 & in [2:0] $end
$var wire 8 ' out [7:0] $end
$upscope $end
$upscope $end
$enddefinitions $end
$comment Show the parameter values. $end
$dumpall
$end
#0
$dumpvars
b1 '
b0 &
b1 %
b0 $
b0 #
b1 "
b1 !
$end
#10
b10 !
b10 '
b10 "
b10 %
b1 #
b1 $
b1 &
#20
b100 !
b100 '
b100 "
b100 %
b10 #
b10 $
b10 &
#30
b1000 !
b1000 '
b1000 "
b1000 %
b11 #
b11 $
b11 &
#40
b10000 !
b10000 '
b10000 "
b10000 %
b100 #
b100 $
b100 &
#50
b100000 !
b100000 '
b100000 "
b100000 %
b101 #
b101 $
b101 &
#60
b1000000 !
b1000000 '
b1000000 "
b1000000 %
b110 #
b110 $
b110 &
#70
b10000000 !
b10000000 '
b10000000 "
b10000000 %
b111 #
b111 $
b111 &
